setup.py
distributions_ex5_zgoey/Binomialdistribution.py
distributions_ex5_zgoey/Gaussiandistribution.py
distributions_ex5_zgoey/Generaldistribution.py
distributions_ex5_zgoey/__init__.py
distributions_ex5_zgoey.egg-info/PKG-INFO
distributions_ex5_zgoey.egg-info/SOURCES.txt
distributions_ex5_zgoey.egg-info/dependency_links.txt
distributions_ex5_zgoey.egg-info/not-zip-safe
distributions_ex5_zgoey.egg-info/top_level.txt